[{"name":"sravani ambati","friends_count":130},{"name":"NIHARIKA","friends_count":24},{"name":"Satling Mukade","friends_count":81},{"name":"Dheeraj","friends_count":199},{"name":"Saikumar Daram","friends_count":6},{"name":"Mamtha Jaanu","friends_count":15},{"name":"PRIYANKA","friends_count":538},{"name":"Amitabh Bachchan","friends_count":1803},{"name":"Vijay Mallya","friends_count":221},{"name":"Hrithik Roshan","friends_count":86},{"name":"Aamir Khan","friends_count":9},{"name":"Deepika Padukone","friends_count":77},{"name":"Virat Kohli","friends_count":52},{"name":"Siddharth","friends_count":73},{"name":"Mahesh Babu","friends_count":1}]
